liteprompt/__init__.py
liteprompt/exceptions.py
liteprompt/prompt.py
liteprompt/registry.py
liteprompt/libs/prompt_poet/__init__.py
liteprompt/libs/prompt_poet/pp_exceptions.py
liteprompt/libs/prompt_poet/prompt.py
liteprompt/libs/prompt_poet/template.py
liteprompt/libs/prompt_poet/template_loaders.py
liteprompt/libs/prompt_poet/template_registry.py
liteprompt/libs/prompt_poet/tokenizer.py
liteprompt/libs/prompt_poet/examples/cai_helpers.py
liteprompt/loaders/__init__.py
liteprompt/loaders/liteCacheLoader.py
liteprompt/loaders/liteGCSDictTemplateLoader.py
liteprompt/loaders/liteLocalFSTemplateLoader.py
liteprompt/loaders/liteLocalPackageTemplateLoader.py
liteprompt/loaders/liteS3AmazonTemplateLoader.py
liteprompt/loaders/liteTemplateLoader.py
liteprompt-0.2.10.dist-info/licenses/LICENSE
liteprompt-0.2.10.dist-info/METADATA
liteprompt-0.2.10.dist-info/WHEEL
liteprompt-0.2.10.dist-info/top_level.txt
liteprompt-0.2.10.dist-info/RECORD
