Metadata-Version: 2.4
Name: liteprompt
Version: 0.2.10
Summary: Lightweight, extensible prompt templating for LLMs
Author: Gianluigi Mucciolo
License: MIT License
Requires-Python: >=3.8
License-File: LICENSE
Requires-Dist: pyyaml>=5.4
Requires-Dist: jinja2>=3.0
Requires-Dist: jinja2schema==0.1.4
Provides-Extra: aws
Requires-Dist: boto3==1.38.13; extra == "aws"
Provides-Extra: cache
Requires-Dist: cachetools==5.3.3; extra == "cache"
Provides-Extra: tokenizer
Requires-Dist: tiktoken==0.7.0; extra == "tokenizer"
Provides-Extra: gcs
Requires-Dist: google-cloud-storage==2.19.0; extra == "gcs"
Dynamic: license-file
